Zapurl
