Metadata-Version: 2.1
Name: Zapurl
Version: 0.1.1
Summary: A tool that allows you to connect directly to ZapURL to shorten link through Python.
Home-page: UNKNOWN
Author: Jonathan Wang
Author-email: jonathanwang2018@gmail.com
License: UNKNOWN
Keywords: URL,Shortener,ZapURL
Platform: UNKNOWN
Classifier: Development Status :: 5 - Production/Stable
Classifier: Intended Audience :: Information Technology
Classifier: Operating System :: OS Independent
Classifier: License :: OSI Approved :: MIT License
Classifier: Programming Language :: Python :: 3
Classifier: Natural Language :: English
